{
  "extension_id": "ekinyuksel12.earths-theme",
  "version": "1.1.0",
  "display_name": "Earth's Theme",
  "publisher_name": "ekinyuksel12",
  "publisher_verified": false,
  "vsix_hash_sha256": "81c2d1687e8705f4099d5c871d24e7077f4819e90b3d4bd04bd40a913a9cd83c",
  "install_count": 3,
  "average_rating": 5.0,
  "published_date": "2026-03-03T11:59:59.077Z",
  "is_blocklisted": false,
  "blocklist_type": "",
  "ai_vibe_score": 0.5,
  "static_analysis_score": 0.7999999999999999,
  "behavioral_score": 0.0,
  "trust_signal_score": 0.7,
  "composite_score": 0.48,
  "verdict": "INFORMATIONAL",
  "confidence": 0.6,
  "total_findings": 2,
  "critical_findings": [],
  "high_findings": [],
  "medium_findings": [
    {
      "severity": "MEDIUM",
      "check_name": "UNVERIFIED_PUBLISHER",
      "description": "Publisher domain is NOT verified by Microsoft",
      "file_path": null,
      "line_number": null,
      "code_snippet": null
    }
  ],
  "info_findings": [
    {
      "severity": "LOW",
      "check_name": "MISSING_DOMAIN",
      "description": "No domain associated with publisher profile",
      "file_path": null,
      "line_number": null,
      "code_snippet": null
    }
  ],
  "iocs": [],
  "ioc_enrichment": [],
  "shared_infrastructure": {},
  "campaign_score": 0.0,
  "vt_detection_count": 0,
  "vt_total_engines": 0,
  "vt_known_malicious": false,
  "escalated_to_chamber": false,
  "escalation_reasons": [],
  "report_timestamp": "2026-03-03T12:21:51.034308+00:00",
  "analysis_duration_seconds": 0.0,
  "raw_ai_response": "AI Vibe Check Fallback: No valid Javascript entry points or YARA targets found. Check backend connectivity to http://192.168.50.98:11434."
}