{
  "extension_id": "TMcQ.clist-language-server",
  "version": "0.1.0",
  "display_name": "IBM CLIST Language Server",
  "publisher_name": "TMcQ",
  "publisher_verified": false,
  "vsix_hash_sha256": "e624800e0b60a353b8fe5be18b20b8f3b2f4a0c28c7276b8a1985fef219d12e0",
  "install_count": 0,
  "average_rating": 0.0,
  "published_date": "2026-02-27T16:53:28.693Z",
  "is_blocklisted": false,
  "blocklist_type": "",
  "ai_vibe_score": 0.7,
  "static_analysis_score": 1.0,
  "behavioral_score": 0.0,
  "trust_signal_score": 0.75,
  "composite_score": 0.6074999999999999,
  "verdict": "SUSPICIOUS",
  "confidence": 0.6,
  "total_findings": 20,
  "critical_findings": [
    {
      "severity": "CRITICAL",
      "check_name": "credential_harvesting",
      "description": "Mass serialization of all environment variables",
      "file_path": "extension/dist/server/server.js",
      "line_number": 8405,
      "code_snippet": "Object.keys(process.env)",
      "category": "credential_harvesting",
      "pattern_id": "env_mass_read"
    },
    {
      "severity": "CRITICAL",
      "check_name": "credential_harvesting",
      "description": "Mass serialization of all environment variables",
      "file_path": "extension/dist/client/extension.js",
      "line_number": 17723,
      "code_snippet": "Object.keys(process.env)",
      "category": "credential_harvesting",
      "pattern_id": "env_mass_read"
    }
  ],
  "high_findings": [
    {
      "severity": "HIGH",
      "check_name": "RISKY_API_CALL",
      "description": "Found 'child_process' pattern",
      "file_path": "extension/dist/server/server.js",
      "line_number": 8311,
      "code_snippet": "var child_process_1 = require(\"child_process\");"
    },
    {
      "severity": "HIGH",
      "check_name": "RISKY_API_CALL",
      "description": "Found 'require(\"child_process\")' pattern",
      "file_path": "extension/dist/server/server.js",
      "line_number": 8311,
      "code_snippet": "var child_process_1 = require(\"child_process\");"
    },
    {
      "severity": "HIGH",
      "check_name": "RISKY_API_CALL",
      "description": "Found 'child_process' pattern",
      "file_path": "extension/dist/server/server.js",
      "line_number": 8369,
      "code_snippet": "let cp = (0, child_process_1.fork)(\"\", [], {"
    },
    {
      "severity": "HIGH",
      "check_name": "RISKY_API_CALL",
      "description": "Found 'child_process' pattern",
      "file_path": "extension/dist/server/server.js",
      "line_number": 8419,
      "code_snippet": "let stdout = (0, child_process_1.spawnSync)(npmCommand, [\"config\", \"get\", \"prefix\"], options).stdout;"
    },
    {
      "severity": "HIGH",
      "check_name": "RISKY_API_CALL",
      "description": "Found 'spawnSync' pattern",
      "file_path": "extension/dist/server/server.js",
      "line_number": 8419,
      "code_snippet": "let stdout = (0, child_process_1.spawnSync)(npmCommand, [\"config\", \"get\", \"prefix\"], options).stdout;"
    },
    {
      "severity": "HIGH",
      "check_name": "RISKY_API_CALL",
      "description": "Found 'child_process' pattern",
      "file_path": "extension/dist/server/server.js",
      "line_number": 8458,
      "code_snippet": "let results = (0, child_process_1.spawnSync)(yarnCommand, [\"global\", \"dir\", \"--json\"], options);"
    },
    {
      "severity": "HIGH",
      "check_name": "RISKY_API_CALL",
      "description": "Found 'spawnSync' pattern",
      "file_path": "extension/dist/server/server.js",
      "line_number": 8458,
      "code_snippet": "let results = (0, child_process_1.spawnSync)(yarnCommand, [\"global\", \"dir\", \"--json\"], options);"
    },
    {
      "severity": "HIGH",
      "check_name": "RISKY_API_CALL",
      "description": "Found 'child_process' pattern",
      "file_path": "extension/dist/client/extension.js",
      "line_number": 16322,
      "code_snippet": "var cp = require(\"child_process\");"
    },
    {
      "severity": "HIGH",
      "check_name": "RISKY_API_CALL",
      "description": "Found 'require(\"child_process\")' pattern",
      "file_path": "extension/dist/client/extension.js",
      "line_number": 16322,
      "code_snippet": "var cp = require(\"child_process\");"
    },
    {
      "severity": "HIGH",
      "check_name": "RISKY_API_CALL",
      "description": "Found 'spawnSync' pattern",
      "file_path": "extension/dist/client/extension.js",
      "line_number": 16344,
      "code_snippet": "var result = cp.spawnSync(cmd, [process2.pid.toString()]);"
    },
    {
      "severity": "HIGH",
      "check_name": "RISKY_API_CALL",
      "description": "Found 'child_process' pattern",
      "file_path": "extension/dist/client/extension.js",
      "line_number": 17563,
      "code_snippet": "var cp = require(\"child_process\");"
    },
    {
      "severity": "HIGH",
      "check_name": "RISKY_API_CALL",
      "description": "Found 'require(\"child_process\")' pattern",
      "file_path": "extension/dist/client/extension.js",
      "line_number": 17563,
      "code_snippet": "var cp = require(\"child_process\");"
    },
    {
      "severity": "HIGH",
      "check_name": "command_execution",
      "description": "Direct command / shell execution",
      "file_path": "extension/dist/server/server.js",
      "line_number": 8311,
      "code_snippet": "require(\"child_process\")",
      "category": "builtin",
      "pattern_id": "command_execution"
    },
    {
      "severity": "HIGH",
      "check_name": "command_execution",
      "description": "Direct command / shell execution",
      "file_path": "extension/dist/client/extension.js",
      "line_number": 16322,
      "code_snippet": "require(\"child_process\")",
      "category": "builtin",
      "pattern_id": "command_execution"
    },
    {
      "severity": "HIGH",
      "check_name": "command_execution",
      "description": "Direct command / shell execution",
      "file_path": "extension/dist/client/extension.js",
      "line_number": 17563,
      "code_snippet": "require(\"child_process\")",
      "category": "builtin",
      "pattern_id": "command_execution"
    }
  ],
  "medium_findings": [
    {
      "severity": "MEDIUM",
      "check_name": "REPO_MISMATCH",
      "description": "Publisher 'tmcq' does not match GitHub org 'chipset' in repo 'https://github.com/chipset/CLIST-LSP.git'",
      "file_path": "package.json",
      "line_number": null,
      "code_snippet": null
    },
    {
      "severity": "MEDIUM",
      "check_name": "UNVERIFIED_PUBLISHER",
      "description": "Publisher domain is NOT verified by Microsoft",
      "file_path": null,
      "line_number": null,
      "code_snippet": null
    }
  ],
  "info_findings": [
    {
      "severity": "LOW",
      "check_name": "MISSING_DOMAIN",
      "description": "No domain associated with publisher profile",
      "file_path": null,
      "line_number": null,
      "code_snippet": null
    }
  ],
  "iocs": [],
  "ioc_enrichment": [],
  "shared_infrastructure": {},
  "campaign_score": 0.0,
  "vt_detection_count": 0,
  "vt_total_engines": 0,
  "vt_known_malicious": false,
  "escalated_to_chamber": true,
  "escalation_reasons": [
    "2 CRITICAL findings",
    "15 HIGH findings",
    "Composite risk 0.62 >= 0.4",
    "AI verdict: SUSPICIOUS"
  ],
  "report_timestamp": "2026-02-27T17:36:51.190169+00:00",
  "analysis_duration_seconds": 0.0,
  "raw_ai_response": "=== extension/dist/server/server.js (chunk 1/5) ===\n```json\n{\n  \"risk_score\": 0.7,\n  \"confidence\": 0.8,\n  \"verdict\": \"SUSPICIOUS\",\n  \"findings\": [\n    {\n      \"severity\": \"CRITICAL\",\n      \"category\": \"credential_harvesting\",\n      \"description\": \"Code reads all environment variables using `Object.keys(process.env)`, which could expose sensitive information.\",\n      \"code_reference\": \"server/server.js (line 8405)\",\n      \"line_hint\": 8405\n    },\n    {\n      \"severity\": \"HIGH\",\n      \"category\": \"builtin\",\n      \"description\": \"Usage of `require('child_process')` which allows arbitrary command execution, posing a high risk if misused.\",\n      \"code_reference\": \"server/server.js (line 8311)\",\n      \"line_hint\": 8311\n    },\n    {\n      \"severity\": \"MEDIUM\",\n      \"category\": \"BEHAVIORAL_MISMATCH\",\n      \"description\": \"Extension's package size (0.2 MB) is appropriate, but the use of `child_process` and environment variable reading may not be documented, indicating a potential capability disconnect.\",\n      \"code_reference\": \"N/A\",\n      \"line_hint\": null\n    }\n  ],\n  \"summary\": \"The extension exhibits high-risk behavior through the use of `child_process` and critical risks via environment variable harvesting. While the package size and activation events align with its purpose, the presence of these elements raises concerns about potential misuse beyond its advertised functionality.\"\n}\n```\n\n=== extension/dist/server/server.js (chunk 2/5) ===\n```json\n{\n  \"risk_score\": 0.1,\n  \"confidence\": 0.8,\n  \"verdict\": \"CLEAN\",\n  \"findings\": [],\n  \"summary\": \"The provided code is part of a standard VS Code extension using the JSON-RPC protocol. It includes typical utility functions for type checking and message handling, with no signs of malicious behavior. The code aligns with expected functionality for extensions requiring RPC communication.\"\n}\n```\n\n=== extension/dist/server/server.js (chunk 3/5) ===\n```json\n{\n  \"risk_score\": 0.1,\n  \"confidence\": 0.85,\n  \"verdict\": \"CLEAN\",\n  \"findings\": [],\n  \"summary\": \"The provided code defines several classes related to handling different types of requests and parameters, but does not exhibit any signs of malicious or suspicious behavior. It appears to be part of a well-structured server implementation with no evidence of secret leakage, credential harvesting, info-stealing, or network exfiltration. The code is clean and aligns with expected behavior for a server component in a VS Code extension.\"\n}\n```\n\n=== extension/dist/server/server.js (chunk 4/5) ===\n```json\n{\n  \"risk_score\": 0.0,\n  \"confidence\": 1.0,\n  \"verdict\": \"CLEAN\",\n  \"findings\": [],\n  \"summary\": \"The provided code defines several classes extending AbstractMessageSignature, which appear to be part of a messaging or protocol handling system. No suspicious or malicious behavior was detected in the code. The functionality appears to be related to message type definitions and does not indicate any security risks.\"\n}\n```\n\n=== extension/dist/server/server.js (chunk 5/5) ===\n```json\n{\n  \"risk_score\": 0.0,\n  \"confidence\": 1.0,\n  \"verdict\": \"CLEAN\",\n  \"findings\": [],\n  \"summary\": \"The provided code appears to be part of a standard VS Code extension handling JSON-RPC messages and notifications. It includes typical message handling logic and uses well-known libraries like vscode-jsonrpc. No suspicious or malicious activities were detected.\"\n}\n```\n\n=== extension/dist/client/extension.js (chunk 1/5) ===\n```json\n{\n  \"risk_score\": 0.7,\n  \"confidence\": 0.6,\n  \"verdict\": \"SUSPICIOUS\",\n  \"findings\": [\n    {\n      \"severity\": \"HIGH\",\n      \"category\": \"command_execution\",\n      \"description\": \"Usage of `require('child_process')` which can enable arbitrary command execution.\",\n      \"code_reference\": \"extension/dist/client/extension.js\",\n      \"line_hint\": 16322\n    },\n    {\n      \"severity\": \"CRITICAL\",\n      \"category\": \"credential_harvesting\",\n      \"description\": \"Mass serialization of environment variables using `Object.keys(process.env)` which could expose sensitive information.\",\n      \"code_reference\": \"extension/dist/client/extension.js\",\n      \"line_hint\": 17723\n    }\n  ],\n  \"summary\": \"The code exhibits potential security risks including arbitrary command execution and environment variable exposure. While these could be part of legitimate functionality, they warrant further investigation to ensure no malicious intent.\"\n}\n```\n\n=== extension/dist/client/extension.js (chunk 2/5) ===\n```json\n{\n  \"risk_score\": 0.1,\n  \"confidence\": 0.9,\n  \"verdict\": \"CLEAN\",\n  \"findings\": [],\n  \"summary\": \"The provided code snippet contains standard type-checking functions and error handling related to JSON-RPC communication. No critical, high-risk, or medium-risk indicators were identified. The code appears to be part of a VS Code extension's client-side implementation, handling basic type validation and error management, which is consistent with expected behavior for such extensions.\"\n}\n```\n\n=== extension/dist/client/extension.js (chunk 3/5) ===\n```json\n{\n  \"risk_score\": 0.1,\n  \"confidence\": 0.8,\n  \"verdict\": \"CLEAN\",\n  \"findings\": [],\n  \"summary\": \"The provided code appears to define message signatures and request types, likely part of a custom protocol or communication mechanism within the VS Code extension. No critical, high, or medium-risk indicators were identified. The code is limited to defining classes and structures, with no evidence of malicious behavior or unauthorized access to system resources.\"\n}\n```\n\n=== extension/dist/client/extension.js (chunk 4/5) ===\n```json\n{\n  \"risk_score\": 0.1,\n  \"confidence\": 0.8,\n  \"verdict\": \"CLEAN\",\n  \"findings\": [],\n  \"summary\": \"The provided code snippet defines various message types (RequestType and NotificationType) extending an AbstractMessageSignature. These appear to be part of a messaging system within the extension, with no evidence of malicious behavior. The code lacks any critical, high-risk, or medium-risk indicators and aligns with standard VS Code extension functionality.\"\n}\n```\n\n=== extension/dist/client/extension.js (chunk 5/5) ===\n```json\n{\n  \"risk_score\": 0.0,\n  \"confidence\": 1.0,\n  \"verdict\": \"CLEAN\",\n  \"findings\": [],\n  \"summary\": \"The provided code snippet is part of a JSON-RPC implementation, specifically handling message validation and management within a VS Code extension. It defines message types (requests, notifications, responses) and a LinkedMap data structure for ordered key access. The code exhibits standard practices for message handling and data structure management, with no evidence of malicious behavior, secret leakage, or unauthorized access. The functionality aligns with expected behaviors for a VS Code extension using JSON-RPC communication.\"\n}\n```"
}